[{"plz_name_long":"50259 Pulheim","lan_code":"05","name":"50259","geo_point_2d":[51.0001948293,6.7841920298],"lan_name":"Nordrhein-Westfalen","krs_name":"Kreis Rhein-Erft-Kreis","plz_code":"50259","krs_code":"05362","plz_name":"Pulheim"},{"plz_name_long":"50127 Bergheim","lan_code":"05","name":"50127","geo_point_2d":[50.9359455465,6.67797935613],"lan_name":"Nordrhein-Westfalen","krs_name":"Kreis Rhein-Erft-Kreis","plz_code":"50127","krs_code":"05362","plz_name":"Bergheim"},{"plz_name_long":"50129 Bergheim","lan_code":"05","name":"50129","geo_point_2d":[50.9809461579,6.70063232013],"lan_name":"Nordrhein-Westfalen","krs_name":"Kreis Rhein-Erft-Kreis","plz_code":"50129","krs_code":"05362","plz_name":"Bergheim"},{"plz_name_long":"50321 Br端hl","lan_code":"05","name":"50321","geo_point_2d":[50.8208863442,6.88665746642],"lan_name":"Nordrhein-Westfalen","krs_name":"Kreis Rhein-Erft-Kreis","plz_code":"50321","krs_code":"05362","plz_name":"Br端hl"},{"plz_name_long":"50389 Wesseling","lan_code":"05","name":"50389","geo_point_2d":[50.817148763,6.97706019364],"lan_name":"Nordrhein-Westfalen","krs_name":"Kreis Rhein-Erft-Kreis","plz_code":"50389","krs_code":"05362","plz_name":"Wesseling"},{"plz_name_long":"50170 Kerpen","lan_code":"05","name":"50170","geo_point_2d":[50.9052023448,6.67385629184],"lan_name":"Nordrhein-Westfalen","krs_name":"Kreis Rhein-Erft-Kreis","plz_code":"50170","krs_code":"05362","plz_name":"Kerpen"},{"plz_name_long":"50126 Bergheim","lan_code":"05","name":"50126","geo_point_2d":[50.9666623459,6.619842408],"lan_name":"Nordrhein-Westfalen","krs_name":"Kreis Rhein-Erft-Kreis","plz_code":"50126","krs_code":"05362","plz_name":"Bergheim"},{"plz_name_long":"50169 Kerpen","lan_code":"05","name":"50169","geo_point_2d":[50.8800313362,6.74563265824],"lan_name":"Nordrhein-Westfalen","krs_name":"Kreis Rhein-Erft-Kreis","plz_code":"50169","krs_code":"05362","plz_name":"Kerpen"},{"plz_name_long":"50374 Erftstadt","lan_code":"05","name":"50374","geo_point_2d":[50.7930177502,6.76687750812],"lan_name":"Nordrhein-Westfalen","krs_name":"Kreis Rhein-Erft-Kreis","plz_code":"50374","krs_code":"05362","plz_name":"Erftstadt"},{"plz_name_long":"50226 Frechen","lan_code":"05","name":"50226","geo_point_2d":[50.9135840286,6.78413770949],"lan_name":"Nordrhein-Westfalen","krs_name":"Kreis Rhein-Erft-Kreis","plz_code":"50226","krs_code":"05362","plz_name":"Frechen"},{"plz_name_long":"50189 Elsdorf","lan_code":"05","name":"50189","geo_point_2d":[50.9318330484,6.56232863079],"lan_name":"Nordrhein-Westfalen","krs_name":"Kreis Rhein-Erft-Kreis","plz_code":"50189","krs_code":"05362","plz_name":"Elsdorf"},{"plz_name_long":"50181 Bedburg","lan_code":"05","name":"50181","geo_point_2d":[51.0099357733,6.54508964214],"lan_name":"Nordrhein-Westfalen","krs_name":"Kreis Rhein-Erft-Kreis","plz_code":"50181","krs_code":"05362","plz_name":"Bedburg"},{"plz_name_long":"50170 Kerpen","lan_code":"05","name":"50170","geo_point_2d":[50.875383243,6.59052125555],"lan_name":"Nordrhein-Westfalen","krs_name":"Kreis Rhein-Erft-Kreis","plz_code":"50170","krs_code":"05362","plz_name":"Kerpen"},{"plz_name_long":"50354 H端rth","lan_code":"05","name":"50354","geo_point_2d":[50.8738680383,6.85887045324],"lan_name":"Nordrhein-Westfalen","krs_name":"Kreis Rhein-Erft-Kreis","plz_code":"50354","krs_code":"05362","plz_name":"H端rth"},{"plz_name_long":"50171 Kerpen","lan_code":"05","name":"50171","geo_point_2d":[50.8625796711,6.66409696759],"lan_name":"Nordrhein-Westfalen","krs_name":"Kreis Rhein-Erft-Kreis","plz_code":"50171","krs_code":"05362","plz_name":"Kerpen"}]